{
  "properties": [
    {
      "name": "app.jwt.jwks-uri",
      "type": "java.lang.String",
      "description": "JWKS endpoint used by the gateway to validate JWT signatures."
    },
    {
      "name": "app.jwt.jwks-cache-seconds",
      "type": "java.lang.Long",
      "description": "TTL for cached JWKS responses in seconds."
    },
    {
      "name": "app.security.token-blacklist.l1.max-size",
      "type": "java.lang.Long",
      "description": "Maximum size of the in-memory token blacklist cache."
    },
    {
      "name": "app.security.token-blacklist.l1.ttl-seconds",
      "type": "java.lang.Long",
      "description": "TTL for the in-memory token blacklist cache in seconds."
    }
  ]
}